artcraft/__init__.py
artcraft/hub/__init__.py
artcraft/hub/model.py
artcraft/hub/resource.py
artcraft/hub/scripts/__init__.py
artcraft/hub/scripts/convert_original_stable_diffusion_to_diffusers.py
artcraft/pipeline/__init__.py
artcraft/pipeline/adapt.py
artcraft/pipeline/diffusion.py
artcraft/pipeline/upscale.py
artcraft/pipeline/custom/__init__.py
artcraft/pipeline/custom/lpw.py
artcraft/pipeline/ip_adapter/__init__.py
artcraft/pipeline/ip_adapter/attention_processor.py
artcraft/pipeline/ip_adapter/attention_processor_faceid.py
artcraft/pipeline/ip_adapter/custom_pipelines.py
artcraft/pipeline/ip_adapter/ip_adapter.py
artcraft/pipeline/ip_adapter/ip_adapter_faceid.py
artcraft/pipeline/ip_adapter/ip_adapter_faceid_separate.py
artcraft/pipeline/ip_adapter/resampler.py
artcraft/pipeline/ip_adapter/test_resampler.py
artcraft/pipeline/ip_adapter/utils.py
artcraft/pipeline/my_gfpgan/__init__.py
artcraft/pipeline/my_gfpgan/utils.py
artcraft/scheme/__init__.py
artcraft/scheme/cache.py
artcraft/scheme/scheme.py
artcraft_ui/__init__.py
artcraft_ui/globals.py
artcraft_ui/hub.py
artcraft_ui/img2img.py
artcraft_ui/launch.py
artcraft_ui/text2img.py
artcraft_ui/util.py
artcraft_ui/gradio/__init__.py
artcraft_ui/gradio/gradio.py
artcraft-1.0.8.dist-info/METADATA
artcraft-1.0.8.dist-info/WHEEL
artcraft-1.0.8.dist-info/top_level.txt
artcraft-1.0.8.dist-info/RECORD
